evolvishub_outlook_ingestor/__init__.py
evolvishub_outlook_ingestor/py.typed
evolvishub_outlook_ingestor/connectors/__init__.py
evolvishub_outlook_ingestor/connectors/aws_s3_connector.py
evolvishub_outlook_ingestor/connectors/azure_blob_connector.py
evolvishub_outlook_ingestor/connectors/base_connector.py
evolvishub_outlook_ingestor/connectors/base_storage_connector.py
evolvishub_outlook_ingestor/connectors/clickhouse_connector.py
evolvishub_outlook_ingestor/connectors/cockroachdb_connector.py
evolvishub_outlook_ingestor/connectors/database_connector.py
evolvishub_outlook_ingestor/connectors/deltalake_connector.py
evolvishub_outlook_ingestor/connectors/gcs_connector.py
evolvishub_outlook_ingestor/connectors/iceberg_connector.py
evolvishub_outlook_ingestor/connectors/mariadb_connector.py
evolvishub_outlook_ingestor/connectors/minio_connector.py
evolvishub_outlook_ingestor/connectors/mongodb_connector.py
evolvishub_outlook_ingestor/connectors/mssql_connector.py
evolvishub_outlook_ingestor/connectors/oracle_connector.py
evolvishub_outlook_ingestor/connectors/postgresql_connector.py
evolvishub_outlook_ingestor/connectors/sqlite_connector.py
evolvishub_outlook_ingestor/core/__init__.py
evolvishub_outlook_ingestor/core/base_processor.py
evolvishub_outlook_ingestor/core/config.py
evolvishub_outlook_ingestor/core/data_models.py
evolvishub_outlook_ingestor/core/email_ingestor.py
evolvishub_outlook_ingestor/core/enhanced_html_converter.py
evolvishub_outlook_ingestor/core/exceptions.py
evolvishub_outlook_ingestor/core/ingestor.py
evolvishub_outlook_ingestor/core/interfaces.py
evolvishub_outlook_ingestor/core/logging.py
evolvishub_outlook_ingestor/core/thread_builder.py
evolvishub_outlook_ingestor/processors/__init__.py
evolvishub_outlook_ingestor/processors/attachment_processor.py
evolvishub_outlook_ingestor/processors/email_processor.py
evolvishub_outlook_ingestor/processors/enhanced_attachment_processor.py
evolvishub_outlook_ingestor/protocols/__init__.py
evolvishub_outlook_ingestor-2.2.3.dist-info/licenses/LICENSE
evolvishub_outlook_ingestor-2.2.3.dist-info/METADATA
evolvishub_outlook_ingestor-2.2.3.dist-info/WHEEL
evolvishub_outlook_ingestor-2.2.3.dist-info/entry_points.txt
evolvishub_outlook_ingestor-2.2.3.dist-info/top_level.txt
evolvishub_outlook_ingestor-2.2.3.dist-info/RECORD
