Metadata-Version: 2.4
Name: evolvishub-outlook-ingestor
Version: 2.2.3
Summary: Enterprise-ready email ingestion system with unified database connector architecture supporting 8 database types with equal implementation quality
Author-email: "Alban Maxhuni, PhD" <a.maxhuni@evolvis.ai>
Maintainer-email: Kevin Medina Gómez <k.medina@evolvis.ai>
License: Evolvis AI License
Project-URL: Homepage, https://github.com/evolvisai/metcal
Project-URL: Documentation, https://github.com/evolvisai/metcal/tree/main/shared/libs/evolvis-outlook-ingestor/docs
Project-URL: Repository, https://github.com/evolvisai/metcal.git
Project-URL: Issues, https://github.com/evolvisai/metcal/issues
Project-URL: Changelog, https://github.com/evolvisai/metcal/blob/main/shared/libs/evolvis-outlook-ingestor/CHANGELOG.md
Project-URL: Examples, https://github.com/evolvisai/metcal/tree/main/shared/libs/evolvis-outlook-ingestor/examples
Keywords: outlook,email,ingestion,exchange,graph-api,imap,pop3,database,async,batch-processing,security,monitoring,performance,postgresql,mongodb,sqlite,cockroachdb,mariadb,mssql,oracle,clickhouse,database-connector,enterprise,standardization
Classifier: Development Status :: 5 - Production/Stable
Classifier: Intended Audience :: Developers
Classifier: Intended Audience :: System Administrators
Classifier: Intended Audience :: Information Technology
Classifier: License :: Other/Proprietary License
Classifier: Operating System :: OS Independent
Classifier: Programming Language :: Python :: 3
Classifier: Programming Language :: Python :: 3.9
Classifier: Programming Language :: Python :: 3.10
Classifier: Programming Language :: Python :: 3.11
Classifier: Programming Language :: Python :: 3.12
Classifier: Topic :: Communications :: Email
Classifier: Topic :: Communications :: Email :: Filters
Classifier: Topic :: Database
Classifier: Topic :: Database :: Database Engines/Servers
Classifier: Topic :: Internet :: WWW/HTTP
Classifier: Topic :: Software Development :: Libraries :: Python Modules
Classifier: Topic :: System :: Archiving
Classifier: Topic :: System :: Monitoring
Classifier: Topic :: System :: Systems Administration
Classifier: Topic :: Security
Classifier: Topic :: Security :: Cryptography
Classifier: Framework :: AsyncIO
Classifier: Framework :: Pydantic
Classifier: Environment :: Console
Classifier: Environment :: Web Environment
Classifier: Typing :: Typed
Requires-Python: >=3.9
License-File: LICENSE
Requires-Dist: pydantic<3.0.0,>=2.0.0
Requires-Dist: pydantic-settings<3.0.0,>=2.0.0
Requires-Dist: typing-extensions>=4.0.0
Requires-Dist: PyYAML>=6.0
Requires-Dist: aiohttp>=3.8.0
Requires-Dist: aiofiles>=23.0.0
Requires-Dist: asyncio-throttle>=1.0.0
Requires-Dist: exchangelib>=5.0.0
Requires-Dist: msal>=1.20.0
Requires-Dist: requests>=2.28.0
Requires-Dist: aioimaplib>=1.0.0
Requires-Dist: sqlalchemy[asyncio]>=2.0.0
Requires-Dist: asyncpg>=0.28.0
Requires-Dist: aiomysql>=0.2.0
Requires-Dist: motor>=3.0.0
Requires-Dist: prometheus-client>=0.17.0
Requires-Dist: structlog>=23.0.0
Requires-Dist: tenacity>=8.0.0
Requires-Dist: psutil>=5.9.0
Requires-Dist: python-dateutil>=2.8.0
Requires-Dist: email-validator>=2.0.0
Requires-Dist: chardet>=5.0.0
Requires-Dist: python-magic>=0.4.0
Requires-Dist: cryptography>=41.0.0
Requires-Dist: beautifulsoup4>=4.11.0
Requires-Dist: Pillow>=9.0.0
Requires-Dist: click>=8.0.0
Requires-Dist: rich>=13.0.0
Requires-Dist: redis>=4.5.0
Requires-Dist: websockets>=11.0.0
Requires-Dist: fastapi>=0.100.0
Requires-Dist: uvicorn>=0.23.0
Requires-Dist: pandas>=2.0.0
Requires-Dist: numpy>=1.24.0
Requires-Dist: scikit-learn>=1.3.0
Requires-Dist: spacy>=3.6.0
Requires-Dist: textblob>=0.17.0
Requires-Dist: langdetect>=1.0.9
Requires-Dist: opentelemetry-api>=1.20.0
Requires-Dist: opentelemetry-sdk>=1.20.0
Requires-Dist: prometheus-client>=0.17.0
Requires-Dist: schedule>=1.2.0
Requires-Dist: cachetools>=5.3.0
Provides-Extra: protocols
Requires-Dist: msal>=1.20.0; extra == "protocols"
Requires-Dist: aiohttp>=3.8.0; extra == "protocols"
Requires-Dist: exchangelib>=5.0.0; extra == "protocols"
Requires-Dist: aioimaplib>=1.0.0; extra == "protocols"
Provides-Extra: database
Requires-Dist: asyncpg>=0.28.0; extra == "database"
Requires-Dist: motor>=3.1.0; extra == "database"
Requires-Dist: aiomysql>=0.1.0; extra == "database"
Provides-Extra: database-sqlite
Requires-Dist: aiosqlite>=0.19.0; extra == "database-sqlite"
Provides-Extra: database-mssql
Requires-Dist: aioodbc>=0.4.0; extra == "database-mssql"
Requires-Dist: pyodbc>=4.0.0; extra == "database-mssql"
Provides-Extra: database-mariadb
Requires-Dist: aiomysql>=0.2.0; extra == "database-mariadb"
Provides-Extra: database-oracle
Requires-Dist: cx_Oracle>=8.3.0; extra == "database-oracle"
Provides-Extra: database-cockroachdb
Requires-Dist: asyncpg>=0.28.0; extra == "database-cockroachdb"
Provides-Extra: database-all
Requires-Dist: asyncpg>=0.28.0; extra == "database-all"
Requires-Dist: motor>=3.1.0; extra == "database-all"
Requires-Dist: aiomysql>=0.2.0; extra == "database-all"
Requires-Dist: aiosqlite>=0.19.0; extra == "database-all"
Requires-Dist: aioodbc>=0.4.0; extra == "database-all"
Requires-Dist: pyodbc>=4.0.0; extra == "database-all"
Requires-Dist: cx_Oracle>=8.3.0; extra == "database-all"
Provides-Extra: datalake-delta
Requires-Dist: delta-spark>=2.4.0; extra == "datalake-delta"
Requires-Dist: pyspark>=3.4.0; extra == "datalake-delta"
Requires-Dist: pyarrow>=12.0.0; extra == "datalake-delta"
Provides-Extra: datalake-iceberg
Requires-Dist: pyiceberg>=0.5.0; extra == "datalake-iceberg"
Requires-Dist: pyarrow>=12.0.0; extra == "datalake-iceberg"
Provides-Extra: database-clickhouse
Requires-Dist: clickhouse-connect>=0.6.0; extra == "database-clickhouse"
Requires-Dist: aiohttp>=3.8.0; extra == "database-clickhouse"
Provides-Extra: datalake-all
Requires-Dist: delta-spark>=2.4.0; extra == "datalake-all"
Requires-Dist: pyspark>=3.4.0; extra == "datalake-all"
Requires-Dist: pyiceberg>=0.5.0; extra == "datalake-all"
Requires-Dist: pyarrow>=12.0.0; extra == "datalake-all"
Requires-Dist: clickhouse-connect>=0.6.0; extra == "datalake-all"
Requires-Dist: aiohttp>=3.8.0; extra == "datalake-all"
Provides-Extra: processing
Requires-Dist: beautifulsoup4>=4.11.0; extra == "processing"
Requires-Dist: Pillow>=9.0.0; extra == "processing"
Provides-Extra: storage
Requires-Dist: minio>=7.1.0; extra == "storage"
Provides-Extra: cloud-aws
Requires-Dist: boto3>=1.26.0; extra == "cloud-aws"
Requires-Dist: botocore>=1.29.0; extra == "cloud-aws"
Provides-Extra: cloud-azure
Requires-Dist: azure-storage-blob>=12.14.0; extra == "cloud-azure"
Requires-Dist: azure-identity>=1.12.0; extra == "cloud-azure"
Provides-Extra: cloud-gcp
Requires-Dist: google-cloud-storage>=2.7.0; extra == "cloud-gcp"
Requires-Dist: google-auth>=2.16.0; extra == "cloud-gcp"
Provides-Extra: cloud-all
Requires-Dist: minio>=7.1.0; extra == "cloud-all"
Requires-Dist: boto3>=1.26.0; extra == "cloud-all"
Requires-Dist: botocore>=1.29.0; extra == "cloud-all"
Requires-Dist: azure-storage-blob>=12.14.0; extra == "cloud-all"
Requires-Dist: azure-identity>=1.12.0; extra == "cloud-all"
Requires-Dist: google-cloud-storage>=2.7.0; extra == "cloud-all"
Requires-Dist: google-auth>=2.16.0; extra == "cloud-all"
Provides-Extra: streaming
Requires-Dist: redis>=4.5.0; extra == "streaming"
Requires-Dist: websockets>=11.0.0; extra == "streaming"
Requires-Dist: fastapi>=0.100.0; extra == "streaming"
Requires-Dist: uvicorn>=0.23.0; extra == "streaming"
Requires-Dist: aiokafka>=0.8.0; extra == "streaming"
Requires-Dist: kafka-python>=2.0.0; extra == "streaming"
Provides-Extra: analytics
Requires-Dist: pandas>=2.0.0; extra == "analytics"
Requires-Dist: numpy>=1.24.0; extra == "analytics"
Requires-Dist: scikit-learn>=1.3.0; extra == "analytics"
Requires-Dist: matplotlib>=3.7.0; extra == "analytics"
Requires-Dist: seaborn>=0.12.0; extra == "analytics"
Requires-Dist: networkx>=3.0; extra == "analytics"
Requires-Dist: scipy>=1.10.0; extra == "analytics"
Provides-Extra: ml
Requires-Dist: spacy>=3.6.0; extra == "ml"
Requires-Dist: textblob>=0.17.0; extra == "ml"
Requires-Dist: langdetect>=1.0.9; extra == "ml"
Requires-Dist: transformers>=4.30.0; extra == "ml"
Requires-Dist: torch>=2.0.0; extra == "ml"
Provides-Extra: observability
Requires-Dist: opentelemetry-api>=1.20.0; extra == "observability"
Requires-Dist: opentelemetry-sdk>=1.20.0; extra == "observability"
Requires-Dist: opentelemetry-instrumentation>=0.41b0; extra == "observability"
Requires-Dist: jaeger-client>=4.8.0; extra == "observability"
Provides-Extra: caching
Requires-Dist: redis>=4.5.0; extra == "caching"
Requires-Dist: cachetools>=5.3.0; extra == "caching"
Requires-Dist: diskcache>=5.6.0; extra == "caching"
Provides-Extra: governance
Requires-Dist: apache-airflow>=2.7.0; extra == "governance"
Requires-Dist: great-expectations>=0.17.0; extra == "governance"
Requires-Dist: dbt-core>=1.6.0; extra == "governance"
Provides-Extra: all
Requires-Dist: msal>=1.20.0; extra == "all"
Requires-Dist: aiohttp>=3.8.0; extra == "all"
Requires-Dist: exchangelib>=5.0.0; extra == "all"
Requires-Dist: aioimaplib>=1.0.0; extra == "all"
Requires-Dist: asyncpg>=0.28.0; extra == "all"
Requires-Dist: motor>=3.1.0; extra == "all"
Requires-Dist: aiomysql>=0.2.0; extra == "all"
Requires-Dist: aiosqlite>=0.19.0; extra == "all"
Requires-Dist: aioodbc>=0.4.0; extra == "all"
Requires-Dist: pyodbc>=4.0.0; extra == "all"
Requires-Dist: cx_Oracle>=8.3.0; extra == "all"
Requires-Dist: clickhouse-connect>=0.6.0; extra == "all"
Requires-Dist: delta-spark>=2.4.0; extra == "all"
Requires-Dist: pyspark>=3.4.0; extra == "all"
Requires-Dist: pyiceberg>=0.5.0; extra == "all"
Requires-Dist: pyarrow>=12.0.0; extra == "all"
Requires-Dist: beautifulsoup4>=4.11.0; extra == "all"
Requires-Dist: Pillow>=9.0.0; extra == "all"
Requires-Dist: minio>=7.1.0; extra == "all"
Requires-Dist: boto3>=1.26.0; extra == "all"
Requires-Dist: botocore>=1.29.0; extra == "all"
Requires-Dist: azure-storage-blob>=12.14.0; extra == "all"
Requires-Dist: azure-identity>=1.12.0; extra == "all"
Requires-Dist: google-cloud-storage>=2.7.0; extra == "all"
Requires-Dist: google-auth>=2.16.0; extra == "all"
Provides-Extra: dev
Requires-Dist: pytest>=7.0.0; extra == "dev"
Requires-Dist: pytest-asyncio>=0.21.0; extra == "dev"
Requires-Dist: pytest-cov>=4.0.0; extra == "dev"
Requires-Dist: pytest-mock>=3.10.0; extra == "dev"
Requires-Dist: pytest-xdist>=3.0.0; extra == "dev"
Requires-Dist: pytest-benchmark>=4.0.0; extra == "dev"
Requires-Dist: black>=23.0.0; extra == "dev"
Requires-Dist: isort>=5.12.0; extra == "dev"
Requires-Dist: mypy>=1.0.0; extra == "dev"
Requires-Dist: flake8>=6.0.0; extra == "dev"
Requires-Dist: bandit>=1.7.0; extra == "dev"
Requires-Dist: sphinx>=6.0.0; extra == "dev"
Requires-Dist: sphinx-rtd-theme>=1.2.0; extra == "dev"
Requires-Dist: myst-parser>=1.0.0; extra == "dev"
Requires-Dist: msal>=1.20.0; extra == "dev"
Requires-Dist: aiohttp>=3.8.0; extra == "dev"
Requires-Dist: exchangelib>=5.0.0; extra == "dev"
Requires-Dist: aioimaplib>=1.0.0; extra == "dev"
Requires-Dist: asyncpg>=0.28.0; extra == "dev"
Requires-Dist: motor>=3.1.0; extra == "dev"
Requires-Dist: aiomysql>=0.1.0; extra == "dev"
Requires-Dist: beautifulsoup4>=4.11.0; extra == "dev"
Requires-Dist: Pillow>=9.0.0; extra == "dev"
Provides-Extra: performance
Requires-Dist: uvloop>=0.17.0; sys_platform != "win32" and extra == "performance"
Requires-Dist: orjson>=3.8.0; extra == "performance"
Requires-Dist: msgpack>=1.0.0; extra == "performance"
Provides-Extra: monitoring
Requires-Dist: grafana-client>=3.5.0; extra == "monitoring"
Requires-Dist: elasticsearch>=8.0.0; extra == "monitoring"
Requires-Dist: redis>=4.5.0; extra == "monitoring"
Dynamic: license-file
